impersonate_permissions/__init__.py
impersonate_permissions/admin.py
impersonate_permissions/apps.py
impersonate_permissions/context_processors.py
impersonate_permissions/middleware.py
impersonate_permissions/migrations/0001_initial.py
impersonate_permissions/migrations/__init__.py
impersonate_permissions/models.py
impersonate_permissions/settings.py
impersonate_permissions/templates/impersonate_permissions/expired.tpl
impersonate_permissions/templates/impersonate_permissions/impersonated.tpl
impersonate_permissions/templates/impersonate_permissions/impersonating.tpl
django_impersonate_permissions-0.4.dist-info/LICENSE
django_impersonate_permissions-0.4.dist-info/WHEEL
django_impersonate_permissions-0.4.dist-info/METADATA
django_impersonate_permissions-0.4.dist-info/RECORD
